{
  "products": [
    {
      "ean": "PIACOND200",
      "modified": "2020-11-10",
      "id": 1,
      "name": "Condicionardor Dove 200ML",
      "price": 5.75,
      "promotional_price": 5.25,
      "start_promotion": "2020-11-17",
      "end_promotion": "2020-11-20",
      "brand": "Dove",
      "stock": 500,
      "category_id": 1,
      "available": 0,
      "url": ["https://superlazzari.com.br/imagem/cache/data/produto/326/5f8f3bd79ca1c_condicionador-dove-reconstrucao-completa-200ml-480x480.jpg"],
      "Variant": "",
      "created": "2017-08-15"
    },
    {
      "ean": "PIAREQ100",
      "modified": "2020-11-10",
      "id": 2,
      "name": "Requeijão Pia",
      "price": 8.95,
      "promotional_price": 8.40,
      "start_promotion": "2020-10-17",
      "end_promotion": "2020-11-10",
      "brand": "Pia",
      "stock": 800,
      "category_id": 1,
      "available": 0,
      "url": ["https://superlazzari.com.br/imagem/cache/data/produto/321/5f734cf476375_produtos_03052018-140101_copotradicional_junto_cpalto-480x480.png"],
      "Variant": "",
      "created": "2019-10-22"
    },
    {
      "ean": "BATCHOC12",
      "modified": "2020-11-01",
      "id": 3,
      "name": "Baton (12 unidades)",
      "price": 18.95,
      "promotional_price": 15.40,
      "start_promotion": "2020-09-17",
      "end_promotion": "2020-11-17",
      "brand": "Baton",
      "stock": 350,
      "category_id": 1,
      "available": 0,
      "url": ["https://superlazzari.com.br/imagem/cache/data/produto/328/5f9ad8d53d9e7_3d3a1eee32-480x480.jpg"],
      "Variant": "",
      "created": "2019-09-22",
      "promotion": 1
    },
    {
      "ean": "SBPPAST4",
      "modified": "2020-10-10",
      "id": 4,
      "name": "Pastilha SBP (4 unidades)",
      "price": 10.95,
      "promotional_price": 9.40,
      "start_promotion": "2020-10-17",
      "end_promotion": "2020-11-25",
      "brand": "SBP",
      "stock": 250,
      "category_id": 1,
      "available": 0,
      "url": ["https://superlazzari.com.br/imagem/cache/data/produto/329/5f9c799d048f3_46799149_1gg-480x480.jpg"],
      "Variant": "",
      "created": "2019-09-21",
      "promotion": 1
    },
    {
      "ean": "PIAIOGU250",
      "modified": "2020-11-14",
      "id": 5,
      "name": "Iogurte 250ml Pia",
      "price": 20.95,
      "promotional_price": 18.40,
      "start_promotion": "2020-08-17",
      "end_promotion": "2020-11-24",
      "brand": "Pia",
      "stock": 254,
      "category_id": 1,
      "available": 0,
      "url": ["https://superlazzari.com.br/imagem/cache/data/produto/335/5faef6ce16b55_unnamed-480x480.png"],
      "Variant": "",
      "created": "2019-09-27",
      "promotion": 1
    }]
}